{"version":3,"kind":"Article","sha256":"879040bd5ffa7ca2b63a3097374492a1068110911ce01a53f318340ac8b8c123","slug":"slos-3","location":"/week03/slos.md","dependencies":[],"frontmatter":{"title":"SLOs","subtitle":"Ordering Results & Calculating Values","authors":[{"nameParsed":{"literal":"Eric Araujo","given":"Eric","family":"Araujo"},"name":"Eric Araujo","email":"eric.araujo@calvin.edu","affiliations":["Calvin University"],"id":"contributors-myst-generated-uid-0","corresponding":true}],"keywords":["SQL","PostgreSQL","databases","relational databases","database management systems","DBMS","data modeling","query optimization"],"affiliations":[{"id":"Calvin University","name":"Calvin University"}],"numbering":{"title":{"offset":2}},"exports":[{"format":"md","filename":"slos.md","url":"/slos-f095ab642c5f6099fd5288e65f02b729.md"}]},"mdast":{"type":"root","children":[{"type":"block","children":[{"type":"heading","depth":2,"position":{"start":{"line":6,"column":1},"end":{"line":6,"column":1}},"children":[{"type":"text","value":"Week 03: April 6–10","position":{"start":{"line":6,"column":1},"end":{"line":6,"column":1}},"key":"UwZ1u1WuCl"}],"identifier":"week-03-april-6-10","label":"Week 03: April 6–10","html_id":"week-03-april-6-10","implicit":true,"key":"LcWtRYglsR"},{"type":"admonition","children":[{"type":"admonitionTitle","children":[{"type":"text","value":"📅 Easter Monday","position":{"start":{"line":8,"column":1},"end":{"line":8,"column":1}},"key":"jEnHm4F2NC"}],"key":"kGd8Vk2EFK"},{"type":"paragraph","position":{"start":{"line":11,"column":1},"end":{"line":11,"column":1}},"children":[{"type":"text","value":"Easter Monday on April 6th. No lecture.","position":{"start":{"line":11,"column":1},"end":{"line":11,"column":1}},"key":"RYDfYSt9FI"}],"key":"ZwYMgJUbr1"}],"icon":false,"class":"note","key":"o8TbGM87Pf"},{"type":"paragraph","position":{"start":{"line":14,"column":1},"end":{"line":14,"column":1}},"children":[{"type":"text","value":"At the end of this week, you should be able to:","position":{"start":{"line":14,"column":1},"end":{"line":14,"column":1}},"key":"Sh36tw8JMz"}],"key":"Gtkmcjh0Le"},{"type":"list","ordered":true,"start":1,"spread":false,"position":{"start":{"line":16,"column":1},"end":{"line":30,"column":1}},"children":[{"type":"listItem","spread":true,"position":{"start":{"line":16,"column":1},"end":{"line":16,"column":1}},"children":[{"type":"paragraph","children":[{"type":"text","value":"Sort query results by multiple columns using ","position":{"start":{"line":16,"column":1},"end":{"line":16,"column":1}},"key":"QMbsleKMAq"},{"type":"inlineCode","value":"ORDER BY","position":{"start":{"line":16,"column":1},"end":{"line":16,"column":1}},"key":"TdMuuJVvXe"},{"type":"text","value":".","position":{"start":{"line":16,"column":1},"end":{"line":16,"column":1}},"key":"HyIlMjvync"}],"key":"ehFpd4do3r"}],"key":"cGdiua7li7"},{"type":"listItem","spread":true,"position":{"start":{"line":17,"column":1},"end":{"line":17,"column":1}},"children":[{"type":"paragraph","children":[{"type":"text","value":"Explain how ","position":{"start":{"line":17,"column":1},"end":{"line":17,"column":1}},"key":"buxdrLd9ec"},{"type":"inlineCode","value":"NULL","position":{"start":{"line":17,"column":1},"end":{"line":17,"column":1}},"key":"eZYf6VMRKg"},{"type":"text","value":" values behave in sorted results.","position":{"start":{"line":17,"column":1},"end":{"line":17,"column":1}},"key":"IITCz7fZyU"}],"key":"FVdVOmu1hi"}],"key":"u2YIlcRL3H"},{"type":"listItem","spread":true,"position":{"start":{"line":18,"column":1},"end":{"line":18,"column":1}},"children":[{"type":"paragraph","children":[{"type":"text","value":"Describe how data types affect sort order.","position":{"start":{"line":18,"column":1},"end":{"line":18,"column":1}},"key":"el3ZSI2YqM"}],"key":"zf2xlgVOOe"}],"key":"tJmTlZs3WW"},{"type":"listItem","spread":true,"position":{"start":{"line":19,"column":1},"end":{"line":19,"column":1}},"children":[{"type":"paragraph","children":[{"type":"text","value":"Limit and paginate results using ","position":{"start":{"line":19,"column":1},"end":{"line":19,"column":1}},"key":"gxr19SGrn8"},{"type":"inlineCode","value":"LIMIT","position":{"start":{"line":19,"column":1},"end":{"line":19,"column":1}},"key":"NReA2amP0L"},{"type":"text","value":" and ","position":{"start":{"line":19,"column":1},"end":{"line":19,"column":1}},"key":"OqniuyCQbi"},{"type":"inlineCode","value":"OFFSET","position":{"start":{"line":19,"column":1},"end":{"line":19,"column":1}},"key":"qr0ttu4NNY"},{"type":"text","value":".","position":{"start":{"line":19,"column":1},"end":{"line":19,"column":1}},"key":"vAdteXgCZX"}],"key":"YvBXxKWKP8"}],"key":"T1scxXP9hH"},{"type":"listItem","spread":true,"position":{"start":{"line":20,"column":1},"end":{"line":20,"column":1}},"children":[{"type":"paragraph","children":[{"type":"text","value":"Write calculated columns in a ","position":{"start":{"line":20,"column":1},"end":{"line":20,"column":1}},"key":"XxXAC8c47T"},{"type":"inlineCode","value":"SELECT","position":{"start":{"line":20,"column":1},"end":{"line":20,"column":1}},"key":"TdB9ChZHVK"},{"type":"text","value":" clause using arithmetic and expressions.","position":{"start":{"line":20,"column":1},"end":{"line":20,"column":1}},"key":"nm4x2uy45Y"}],"key":"wps73uzyvW"}],"key":"lHfK3fFhwj"},{"type":"listItem","spread":true,"position":{"start":{"line":21,"column":1},"end":{"line":21,"column":1}},"children":[{"type":"paragraph","children":[{"type":"text","value":"Handle ","position":{"start":{"line":21,"column":1},"end":{"line":21,"column":1}},"key":"j64iqfdQ8j"},{"type":"inlineCode","value":"NULL","position":{"start":{"line":21,"column":1},"end":{"line":21,"column":1}},"key":"DHId3MRfVm"},{"type":"text","value":" values in calculations using functions like ","position":{"start":{"line":21,"column":1},"end":{"line":21,"column":1}},"key":"riiuXEoAk5"},{"type":"inlineCode","value":"COALESCE","position":{"start":{"line":21,"column":1},"end":{"line":21,"column":1}},"key":"mhQKTihmfX"},{"type":"text","value":" and ","position":{"start":{"line":21,"column":1},"end":{"line":21,"column":1}},"key":"Gan06f4Dy4"},{"type":"inlineCode","value":"NULLIF","position":{"start":{"line":21,"column":1},"end":{"line":21,"column":1}},"key":"JPyGJCkySx"},{"type":"text","value":".","position":{"start":{"line":21,"column":1},"end":{"line":21,"column":1}},"key":"hJDXzKpRFs"}],"key":"NzrX4eRzNI"}],"key":"aRiNlMUqmw"},{"type":"listItem","spread":true,"position":{"start":{"line":22,"column":1},"end":{"line":22,"column":1}},"children":[{"type":"paragraph","children":[{"type":"text","value":"Apply arithmetic operators (","position":{"start":{"line":22,"column":1},"end":{"line":22,"column":1}},"key":"JxSkBEbDIG"},{"type":"inlineCode","value":"+","position":{"start":{"line":22,"column":1},"end":{"line":22,"column":1}},"key":"SUBvNmz19N"},{"type":"text","value":", ","position":{"start":{"line":22,"column":1},"end":{"line":22,"column":1}},"key":"ucbR1ny4ez"},{"type":"inlineCode","value":"-","position":{"start":{"line":22,"column":1},"end":{"line":22,"column":1}},"key":"NbUDrrpWo7"},{"type":"text","value":", ","position":{"start":{"line":22,"column":1},"end":{"line":22,"column":1}},"key":"MUlro5aB0G"},{"type":"inlineCode","value":"*","position":{"start":{"line":22,"column":1},"end":{"line":22,"column":1}},"key":"gGHlb2qGJv"},{"type":"text","value":", ","position":{"start":{"line":22,"column":1},"end":{"line":22,"column":1}},"key":"IWnWcxkuTd"},{"type":"inlineCode","value":"/","position":{"start":{"line":22,"column":1},"end":{"line":22,"column":1}},"key":"bKbzydqww8"},{"type":"text","value":", ","position":{"start":{"line":22,"column":1},"end":{"line":22,"column":1}},"key":"C5sHIfkDVx"},{"type":"inlineCode","value":"%","position":{"start":{"line":22,"column":1},"end":{"line":22,"column":1}},"key":"euyIEdBBBN"},{"type":"text","value":") inside queries.","position":{"start":{"line":22,"column":1},"end":{"line":22,"column":1}},"key":"tXs6hElJ6n"}],"key":"qiNoPIO7IH"}],"key":"f82v50ePuO"},{"type":"listItem","spread":true,"position":{"start":{"line":23,"column":1},"end":{"line":23,"column":1}},"children":[{"type":"paragraph","children":[{"type":"text","value":"Use numeric functions such as ","position":{"start":{"line":23,"column":1},"end":{"line":23,"column":1}},"key":"qih3DwG7u5"},{"type":"inlineCode","value":"ROUND","position":{"start":{"line":23,"column":1},"end":{"line":23,"column":1}},"key":"wDZrjCsc1P"},{"type":"text","value":", ","position":{"start":{"line":23,"column":1},"end":{"line":23,"column":1}},"key":"X6j63nh6cg"},{"type":"inlineCode","value":"FLOOR","position":{"start":{"line":23,"column":1},"end":{"line":23,"column":1}},"key":"CixPV8SkAI"},{"type":"text","value":", and ","position":{"start":{"line":23,"column":1},"end":{"line":23,"column":1}},"key":"n2psFG16f2"},{"type":"inlineCode","value":"CEIL","position":{"start":{"line":23,"column":1},"end":{"line":23,"column":1}},"key":"ZgshKJcO8N"},{"type":"text","value":" to transform values.","position":{"start":{"line":23,"column":1},"end":{"line":23,"column":1}},"key":"C5U2vnHNL2"}],"key":"Va3tujjeRp"}],"key":"HQL5O16xx9"},{"type":"listItem","spread":true,"position":{"start":{"line":24,"column":1},"end":{"line":24,"column":1}},"children":[{"type":"paragraph","children":[{"type":"text","value":"Use datetime functions to extract and manipulate date and time data.","position":{"start":{"line":24,"column":1},"end":{"line":24,"column":1}},"key":"NlSR30vlAA"}],"key":"dxY38OlE6f"}],"key":"zr3743kWjo"},{"type":"listItem","spread":true,"position":{"start":{"line":25,"column":1},"end":{"line":25,"column":1}},"children":[{"type":"paragraph","children":[{"type":"text","value":"Use string functions such as ","position":{"start":{"line":25,"column":1},"end":{"line":25,"column":1}},"key":"V3wVw8IOy8"},{"type":"inlineCode","value":"UPPER","position":{"start":{"line":25,"column":1},"end":{"line":25,"column":1}},"key":"mqQFb14N6H"},{"type":"text","value":", ","position":{"start":{"line":25,"column":1},"end":{"line":25,"column":1}},"key":"GWtFDVHHTS"},{"type":"inlineCode","value":"TRIM","position":{"start":{"line":25,"column":1},"end":{"line":25,"column":1}},"key":"pizONMnUF6"},{"type":"text","value":", and ","position":{"start":{"line":25,"column":1},"end":{"line":25,"column":1}},"key":"lXMTho3gqE"},{"type":"inlineCode","value":"SUBSTR","position":{"start":{"line":25,"column":1},"end":{"line":25,"column":1}},"key":"L98bDwXLkJ"},{"type":"text","value":" to transform text.","position":{"start":{"line":25,"column":1},"end":{"line":25,"column":1}},"key":"PtT1o2cShA"}],"key":"khWLlFnHFs"}],"key":"UpeEbB3FKP"},{"type":"listItem","spread":true,"position":{"start":{"line":26,"column":1},"end":{"line":26,"column":1}},"children":[{"type":"paragraph","children":[{"type":"text","value":"Write a basic subquery nested inside a ","position":{"start":{"line":26,"column":1},"end":{"line":26,"column":1}},"key":"Ywqobvhob5"},{"type":"inlineCode","value":"SELECT","position":{"start":{"line":26,"column":1},"end":{"line":26,"column":1}},"key":"eHQcq1ytik"},{"type":"text","value":" or ","position":{"start":{"line":26,"column":1},"end":{"line":26,"column":1}},"key":"yDwFAVIo1Z"},{"type":"inlineCode","value":"WHERE","position":{"start":{"line":26,"column":1},"end":{"line":26,"column":1}},"key":"PAZFdwyKjf"},{"type":"text","value":" clause.","position":{"start":{"line":26,"column":1},"end":{"line":26,"column":1}},"key":"qJroX0wiGz"}],"key":"PiR5I6E987"}],"key":"KITdIoizar"},{"type":"listItem","spread":true,"position":{"start":{"line":27,"column":1},"end":{"line":27,"column":1}},"children":[{"type":"paragraph","children":[{"type":"text","value":"Use a ","position":{"start":{"line":27,"column":1},"end":{"line":27,"column":1}},"key":"nlZhEbOxPM"},{"type":"inlineCode","value":"CASE","position":{"start":{"line":27,"column":1},"end":{"line":27,"column":1}},"key":"CRlDq9bVKb"},{"type":"text","value":" expression to return conditional values within a query.","position":{"start":{"line":27,"column":1},"end":{"line":27,"column":1}},"key":"y4BZ9fFPtJ"}],"key":"BS4zcviFPS"}],"key":"vSIGxWgvmr"},{"type":"listItem","spread":true,"position":{"start":{"line":28,"column":1},"end":{"line":28,"column":1}},"children":[{"type":"paragraph","children":[{"type":"text","value":"Convert between data types using ","position":{"start":{"line":28,"column":1},"end":{"line":28,"column":1}},"key":"pWwkoIvoMe"},{"type":"inlineCode","value":"CAST","position":{"start":{"line":28,"column":1},"end":{"line":28,"column":1}},"key":"gwkbuJucwM"},{"type":"text","value":".","position":{"start":{"line":28,"column":1},"end":{"line":28,"column":1}},"key":"ziKbpVrmVs"}],"key":"VwL9qAQwGZ"}],"key":"OqQqGUrCs8"},{"type":"listItem","spread":true,"position":{"start":{"line":29,"column":1},"end":{"line":30,"column":1}},"children":[{"type":"paragraph","children":[{"type":"text","value":"Create a reusable ","position":{"start":{"line":29,"column":1},"end":{"line":29,"column":1}},"key":"tFHi4gc8MP"},{"type":"inlineCode","value":"VIEW","position":{"start":{"line":29,"column":1},"end":{"line":29,"column":1}},"key":"cAZDRTKvu5"},{"type":"text","value":" using ","position":{"start":{"line":29,"column":1},"end":{"line":29,"column":1}},"key":"aecECnEaPW"},{"type":"inlineCode","value":"CREATE VIEW","position":{"start":{"line":29,"column":1},"end":{"line":29,"column":1}},"key":"dVVGss7iDO"},{"type":"text","value":".","position":{"start":{"line":29,"column":1},"end":{"line":29,"column":1}},"key":"AjBTadVikK"}],"key":"yd8wFqHF1Y"}],"key":"wkSKJUoM0I"}],"key":"PUrloeLKSV"},{"type":"admonition","children":[{"type":"admonitionTitle","children":[{"type":"text","value":"📖 Readings","position":{"start":{"line":31,"column":1},"end":{"line":31,"column":1}},"key":"OhhbqzRJCp"}],"key":"arfhbjnkJo"},{"type":"paragraph","position":{"start":{"line":34,"column":1},"end":{"line":34,"column":1}},"children":[{"type":"text","value":"Chapters 4 & 5 of ","position":{"start":{"line":34,"column":1},"end":{"line":34,"column":1}},"key":"JLhAEX0wPv"},{"type":"emphasis","position":{"start":{"line":34,"column":1},"end":{"line":34,"column":1}},"children":[{"type":"text","value":"Getting Started with SQL and Databases","position":{"start":{"line":34,"column":1},"end":{"line":34,"column":1}},"key":"kLg2H7442u"}],"key":"ATFAgcrMxM"},{"type":"text","value":" by Mark Simon.","position":{"start":{"line":34,"column":1},"end":{"line":34,"column":1}},"key":"xIARAWLE5K"}],"key":"G372hY8sGM"}],"icon":false,"class":"warning","key":"MLWJ6JEnXA"}],"key":"yaTtt47Bkn"}],"key":"FsbUF6aSWZ"},"references":{"cite":{"order":[],"data":{}}}}